aegis/__init__.py
aegis/decorators.py
aegis/exceptions.py
aegis/matching_algorithms.py
aegis/middlewares.py
aegis/routes.py
aegis/test_utils.py
aegis/authenticators/__init__.py
aegis/authenticators/base.py
aegis/authenticators/basic.py
aegis/authenticators/jwt.py
aegis/authenticators/otp.py
aegis-1.1.1.dist-info/LICENSE
aegis-1.1.1.dist-info/METADATA
aegis-1.1.1.dist-info/WHEEL
aegis-1.1.1.dist-info/top_level.txt
aegis-1.1.1.dist-info/RECORD
