Metadata-Version: 2.1
Name: aegis
Version: 1.1.1
Summary: Authentication library for aiohttp
Home-page: https://github.com/mgurdal/aegis
Author: Mehmet Gurdal
Author-email: mgurdal@protonmail.com
License: Apache 2
Platform: UNKNOWN
Classifier: License :: OSI Approved :: Apache Software License
Classifier: Programming Language :: Python :: 3.6
Classifier: Programming Language :: Python :: 3.7
Classifier: Programming Language :: Python :: 3.8
Classifier: Operating System :: POSIX
Classifier: Operating System :: MacOS :: MacOS X
Classifier: Operating System :: Microsoft :: Windows
Classifier: Topic :: Internet :: WWW/HTTP
Classifier: Framework :: AsyncIO
Classifier: License :: OSI Approved :: Apache Software License
Requires-Python: >=3.6.0
Requires-Dist: aiohttp
Requires-Dist: PyJWT
